colorgetter/__init__.py
colorgetter/main.py
colorgetter-0.0.2.dist-info/LICENSE
colorgetter-0.0.2.dist-info/METADATA
colorgetter-0.0.2.dist-info/WHEEL
colorgetter-0.0.2.dist-info/top_level.txt
colorgetter-0.0.2.dist-info/RECORD
