Metadata-Version: 2.1
Name: colorgetter
Version: 0.0.2
Summary: Python color getter (being able to get random/complementary/lighter/darker color, convert between rgb/hex)
Home-page: https://github.com/yjg30737/colorgetter.git
Author: Jung Gyu Yoon
Author-email: yjg30737@gmail.com
License: MIT
Platform: UNKNOWN
License-File: LICENSE
